sqlfixtures/__init__.py
sqlfixtures/insertable.py
sqlfixtures/py.typed
sqlfixtures/sqlfixture.py
sqlfixtures-0.0.2.dist-info/licenses/LICENSE.txt
sqlfixtures-0.0.2.dist-info/METADATA
sqlfixtures-0.0.2.dist-info/WHEEL
sqlfixtures-0.0.2.dist-info/top_level.txt
sqlfixtures-0.0.2.dist-info/RECORD
