Metadata-Version: 2.4
Name: sqlfixtures
Version: 0.0.2
Summary: Create test fixtures against an SQL database
Author-email: Oliver Cope <oliver@redgecko.org>
Classifier: Programming Language :: Python :: 3
Classifier: License :: OSI Approved :: MIT License
Classifier: Operating System :: OS Independent
Requires-Python: >=3.10
License-File: LICENSE.txt
Requires-Dist: embrace
Dynamic: license-file
